{
  "date": "2026-04-22",
  "generatedAt": "2026-04-22T06:50:25.980878+00:00",
  "version": 1,
  "hero": null,
  "tabs": {
    "current": {
      "politics": [],
      "society": [],
      "international": [],
      "tech": []
    },
    "economy": {
      "indices": [],
      "signals": [
        {
          "id": "20260422000454",
          "source": "dart",
          "company": "대동기어",
          "companyCode": "008830",
          "headline": "주요사항보고서(유무상증자결정)",
          "summary": "",
          "score": 85,
          "direction": "mixed",
          "scope": "domestic",
          "time": "2026-04-22T00:00:00",
          "url": "https://dart.fss.or.kr/dsaf001/main.do?rcpNo=20260422000454",
          "glossaryTermId": null
        },
        {
          "id": "20260422000449",
          "source": "dart",
          "company": "나노실리칸첨단소재",
          "companyCode": "286750",
          "headline": "주요사항보고서(자기전환사채만기전취득결정)",
          "summary": "",
          "score": 85,
          "direction": "mixed",
          "scope": "domestic",
          "time": "2026-04-22T00:00:00",
          "url": "https://dart.fss.or.kr/dsaf001/main.do?rcpNo=20260422000449",
          "glossaryTermId": "convertible_bond"
        },
        {
          "id": "20260422800406",
          "source": "dart",
          "company": "삼성바이오로직스",
          "companyCode": "207940",
          "headline": "연결재무제표기준영업(잠정)실적(공정공시)              ",
          "summary": "",
          "score": 85,
          "direction": "mixed",
          "scope": "domestic",
          "time": "2026-04-22T00:00:00",
          "url": "https://dart.fss.or.kr/dsaf001/main.do?rcpNo=20260422800406",
          "glossaryTermId": "tentative_earnings"
        },
        {
          "id": "20260422000430",
          "source": "dart",
          "company": "인산가",
          "companyCode": "277410",
          "headline": "주요사항보고서(전환사채권발행결정)",
          "summary": "",
          "score": 85,
          "direction": "mixed",
          "scope": "domestic",
          "time": "2026-04-22T00:00:00",
          "url": "https://dart.fss.or.kr/dsaf001/main.do?rcpNo=20260422000430",
          "glossaryTermId": "convertible_bond"
        },
        {
          "id": "20260422900377",
          "source": "dart",
          "company": "이노스페이스",
          "companyCode": "462350",
          "headline": "단일판매ㆍ공급계약체결              ",
          "summary": "",
          "score": 75,
          "direction": "positive",
          "scope": "domestic",
          "time": "2026-04-22T00:00:00",
          "url": "https://dart.fss.or.kr/dsaf001/main.do?rcpNo=20260422900377",
          "glossaryTermId": "big_contract"
        },
        {
          "id": "20260422000460",
          "source": "dart",
          "company": "이뮨온시아",
          "companyCode": "424870",
          "headline": "임원ㆍ주요주주특정증권등소유상황보고서",
          "summary": "",
          "score": 70,
          "direction": "mixed",
          "scope": "domestic",
          "time": "2026-04-22T00:00:00",
          "url": "https://dart.fss.or.kr/dsaf001/main.do?rcpNo=20260422000460",
          "glossaryTermId": "insider_trade"
        },
        {
          "id": "20260422000458",
          "source": "dart",
          "company": "삼천리",
          "companyCode": "004690",
          "headline": "임원ㆍ주요주주특정증권등소유상황보고서",
          "summary": "",
          "score": 70,
          "direction": "mixed",
          "scope": "domestic",
          "time": "2026-04-22T00:00:00",
          "url": "https://dart.fss.or.kr/dsaf001/main.do?rcpNo=20260422000458",
          "glossaryTermId": "insider_trade"
        },
        {
          "id": "20260422000442",
          "source": "dart",
          "company": "팅크웨어",
          "companyCode": "084730",
          "headline": "자기주식처분결과보고서",
          "summary": "",
          "score": 70,
          "direction": "mixed",
          "scope": "domestic",
          "time": "2026-04-22T00:00:00",
          "url": "https://dart.fss.or.kr/dsaf001/main.do?rcpNo=20260422000442",
          "glossaryTermId": "self_stock_sell"
        },
        {
          "id": "20260422900411",
          "source": "dart",
          "company": "대동기어",
          "companyCode": "008830",
          "headline": "주권매매거래정지              (무상증자)",
          "summary": "",
          "score": 60,
          "direction": "positive",
          "scope": "domestic",
          "time": "2026-04-22T00:00:00",
          "url": "https://dart.fss.or.kr/dsaf001/main.do?rcpNo=20260422900411",
          "glossaryTermId": null
        }
      ],
      "news": [
        {
          "id": "https://www.hankyung.com/article/202604229164i",
          "source": "rss:hankyung",
          "title": "중동전쟁에 3월 생산자물가 4년만에 최대폭 상승",
          "summary": "",
          "url": "https://www.hankyung.com/article/202604229164i",
          "thumbnail": null,
          "time": "2026-04-22T06:26:17",
          "scope": "domestic",
          "glossaryTermId": null,
          "curationScore": 0
        },
        {
          "id": "https://www.hankyung.com/article/202604229143i",
          "source": "rss:hankyung",
          "title": "고환율에 환전 수요 증가…3월 외화예금 역대 최대폭 감소",
          "summary": "",
          "url": "https://www.hankyung.com/article/202604229143i",
          "thumbnail": null,
          "time": "2026-04-22T06:20:54",
          "scope": "domestic",
          "glossaryTermId": null,
          "curationScore": 0
        },
        {
          "id": "https://www.hankyung.com/article/202604228885g",
          "source": "rss:hankyung",
          "title": "대상 청정원, 용도형 식초 '피클링소스' 출시…'모노 유즈' 라인업 확대",
          "summary": "",
          "url": "https://www.hankyung.com/article/202604228885g",
          "thumbnail": null,
          "time": "2026-04-22T06:17:49",
          "scope": "domestic",
          "glossaryTermId": null,
          "curationScore": 0
        },
        {
          "id": "https://www.hankyung.com/article/202604229056i",
          "source": "rss:hankyung",
          "title": "기술보증기금, 엘파워텍을 '넷제로멤버스' 기업으로 선정",
          "summary": "",
          "url": "https://www.hankyung.com/article/202604229056i",
          "thumbnail": null,
          "time": "2026-04-22T06:13:25",
          "scope": "domestic",
          "glossaryTermId": null,
          "curationScore": 0
        },
        {
          "id": "https://www.hankyung.com/article/202604229003g",
          "source": "rss:hankyung",
          "title": "\"일자리 1만개 터진다\"…청주 들썩인 SK하이닉스 '잭팟'",
          "summary": "",
          "url": "https://www.hankyung.com/article/202604229003g",
          "thumbnail": null,
          "time": "2026-04-22T06:05:26",
          "scope": "domestic",
          "glossaryTermId": null,
          "curationScore": 0
        },
        {
          "id": "https://www.mk.co.kr/news/politics/12024074",
          "source": "rss:mk",
          "title": "정청래, 정당사 최초 선상 최고위 열어…‘험지’ 경남 세 번째 방문",
          "summary": "鄭, 험지 경남 방문해 김경수 지원사격 욕지도 바다서 선상 최고위 최초 개최 재보궐 전략공천 원칙 재차 강조 나서6·3 지방선거 승리를 위한 지방 공략 행보에 박차를 가하고 있는 ..",
          "url": "https://www.mk.co.kr/news/politics/12024074",
          "thumbnail": null,
          "time": "2026-04-22T06:47:59",
          "scope": "domestic",
          "glossaryTermId": null,
          "curationScore": 0
        },
        {
          "id": "https://www.mk.co.kr/news/economy/12024071",
          "source": "rss:mk",
          "title": "“4월 월급 보고 놀라지 마세요”…건보료 평균 22만원 더 내는 직장인 1000만명",
          "summary": "작년 ‘임금 인상‘ 및 ’호봉‘ 오른 영향 보험료 부담된다면 ‘분할 납부‘도 가능 감소한 가입자는 평균 11만5천원 환급지난해 임금이나 호봉이 오른 직장가입자 1000만명 이상이 ..",
          "url": "https://www.mk.co.kr/news/economy/12024071",
          "thumbnail": null,
          "time": "2026-04-22T06:47:27",
          "scope": "domestic",
          "glossaryTermId": null,
          "curationScore": 0
        },
        {
          "id": "https://www.mk.co.kr/news/it/12024070",
          "source": "rss:mk",
          "title": "엔씨 ‘아이온2’ 올해 하반기 글로벌 출격",
          "summary": "PC에서 서비스...스팀·퍼플 플랫폼 전용엔씨가 다중접속역할수행게임(MMORPG) ‘아이온2’를 올해 하반기에 글로벌 출시한다고 22일 밝혔다. 아이온2는 엔씨의 대표작 중 하나로..",
          "url": "https://www.mk.co.kr/news/it/12024070",
          "thumbnail": null,
          "time": "2026-04-22T06:47:06",
          "scope": "domestic",
          "glossaryTermId": null,
          "curationScore": 0
        },
        {
          "id": "https://www.mk.co.kr/news/society/12024062",
          "source": "rss:mk",
          "title": "창원상의 “침체된 지역경제, 세제·인재·소비 ‘3축 처방’ 시급”",
          "summary": "법인세 최대 3%p 인하 비수도권, 차등적용해야 산업기능요원 개선·감사제 폐지 필요 지역제품 소비·30개 공약 반영 제안창원상의가 수도권 집중을 완화하기 위한 ‘세제 차등 적용’ ..",
          "url": "https://www.mk.co.kr/news/society/12024062",
          "thumbnail": null,
          "time": "2026-04-22T06:44:22",
          "scope": "domestic",
          "glossaryTermId": null,
          "curationScore": 0
        },
        {
          "id": "https://www.mk.co.kr/news/culture/12024060",
          "source": "rss:mk",
          "title": "“33일의 도망, 결국 나를 만났다”…‘K팝 기획자’ 나상천, 첫 장편 ‘어느 멋진 도망’ 출간",
          "summary": "산티아고 800km에 담은 상처와 치유 연재 흥행→뮤지컬 확장까지K팝 기획자이자 극작가인 나상천이 첫 장편소설을 내놓으며 소설가로 데뷔했다. 22일 KT 밀리의서재의 출판 브랜드 ..",
          "url": "https://www.mk.co.kr/news/culture/12024060",
          "thumbnail": null,
          "time": "2026-04-22T06:41:23",
          "scope": "domestic",
          "glossaryTermId": null,
          "curationScore": 0
        },
        {
          "id": "https://www.mk.co.kr/news/stock/12024059",
          "source": "rss:mk",
          "title": "[속보] 코스피, 6417 돌파…하루 만에 최고치 또 경신",
          "summary": "",
          "url": "https://www.mk.co.kr/news/stock/12024059",
          "thumbnail": null,
          "time": "2026-04-22T06:37:15",
          "scope": "domestic",
          "glossaryTermId": null,
          "curationScore": 0
        },
        {
          "id": "https://www.mk.co.kr/news/stock/12024058",
          "source": "rss:mk",
          "title": "코스피 마감, 6,417.93P (0.46%↑) HD현대중공업, 한화에어로스페등 상승세",
          "summary": "업종을 살펴보면 코스피 금속 업종이 전일 대비 3.0% 오르며 상승이 두드러졌고, 그 외에도 코스피 운송장비·부품(2.71%), 코스피 화학(1.56%), 코스피 의료·정밀기기(1..",
          "url": "https://www.mk.co.kr/news/stock/12024058",
          "thumbnail": null,
          "time": "2026-04-22T06:37:00",
          "scope": "domestic",
          "glossaryTermId": null,
          "curationScore": 0
        },
        {
          "id": "https://www.mk.co.kr/news/stock/12024056",
          "source": "rss:mk",
          "title": "코스닥 마감, 1,181.12P (0.18%↑) 리노공업, 에코프로등 상승세",
          "summary": "22일 코스닥지수는 전 거래일 대비 +2.09 포인트(0.18%) 오른 1,181.12로 장마감했다.업종별로는 코스닥 화학(2.68%), 코스닥 금융(2.26%), 코스닥 금속(1..",
          "url": "https://www.mk.co.kr/news/stock/12024056",
          "thumbnail": null,
          "time": "2026-04-22T06:35:50",
          "scope": "domestic",
          "glossaryTermId": null,
          "curationScore": 0
        },
        {
          "id": "https://www.mk.co.kr/news/society/12024055",
          "source": "rss:mk",
          "title": "작년 ‘바늘구멍’ 의대에 1.0등급 89% 몰렸다",
          "summary": "진학사 2026학년도 수시모집 의대 지원 분석지난 2026학년도 수시에서 의대 모집인원은 줄어들었지만 내신 1.0등급대 최상위권의 의대 쏠림이 오히려 더 심했던 것으로 나타났다. ..",
          "url": "https://www.mk.co.kr/news/society/12024055",
          "thumbnail": null,
          "time": "2026-04-22T06:35:13",
          "scope": "domestic",
          "glossaryTermId": null,
          "curationScore": 0
        },
        {
          "id": "https://www.mk.co.kr/news/economy/12024054",
          "source": "rss:mk",
          "title": "고객정보로 보험내용 바꾼 보험설계사…대법 “설계사는 개인정보처리자 아냐”",
          "summary": "유죄 선고한 2심 파기환송고객의 개인정보를 이용해 보험내용 변경을 신청한 혐의로 기소된 보험설계사를 ‘개인정보처리자’로 보고 처벌한 것은 잘못됐다는 대법원 판단이 나왔다. 22일 ..",
          "url": "https://www.mk.co.kr/news/economy/12024054",
          "thumbnail": null,
          "time": "2026-04-22T06:33:57",
          "scope": "domestic",
          "glossaryTermId": null,
          "curationScore": 0
        }
      ]
    },
    "picks": {
      "domestic": [
        {
          "id": "20260422000454",
          "source": "dart",
          "company": "대동기어",
          "companyCode": "008830",
          "headline": "주요사항보고서(유무상증자결정)",
          "summary": "",
          "score": 85,
          "direction": "mixed",
          "scope": "domestic",
          "time": "2026-04-22T00:00:00",
          "url": "https://dart.fss.or.kr/dsaf001/main.do?rcpNo=20260422000454",
          "glossaryTermId": null
        },
        {
          "id": "20260422000449",
          "source": "dart",
          "company": "나노실리칸첨단소재",
          "companyCode": "286750",
          "headline": "주요사항보고서(자기전환사채만기전취득결정)",
          "summary": "",
          "score": 85,
          "direction": "mixed",
          "scope": "domestic",
          "time": "2026-04-22T00:00:00",
          "url": "https://dart.fss.or.kr/dsaf001/main.do?rcpNo=20260422000449",
          "glossaryTermId": "convertible_bond"
        },
        {
          "id": "20260422800406",
          "source": "dart",
          "company": "삼성바이오로직스",
          "companyCode": "207940",
          "headline": "연결재무제표기준영업(잠정)실적(공정공시)              ",
          "summary": "",
          "score": 85,
          "direction": "mixed",
          "scope": "domestic",
          "time": "2026-04-22T00:00:00",
          "url": "https://dart.fss.or.kr/dsaf001/main.do?rcpNo=20260422800406",
          "glossaryTermId": "tentative_earnings"
        },
        {
          "id": "20260422000430",
          "source": "dart",
          "company": "인산가",
          "companyCode": "277410",
          "headline": "주요사항보고서(전환사채권발행결정)",
          "summary": "",
          "score": 85,
          "direction": "mixed",
          "scope": "domestic",
          "time": "2026-04-22T00:00:00",
          "url": "https://dart.fss.or.kr/dsaf001/main.do?rcpNo=20260422000430",
          "glossaryTermId": "convertible_bond"
        },
        {
          "id": "20260422900377",
          "source": "dart",
          "company": "이노스페이스",
          "companyCode": "462350",
          "headline": "단일판매ㆍ공급계약체결              ",
          "summary": "",
          "score": 75,
          "direction": "positive",
          "scope": "domestic",
          "time": "2026-04-22T00:00:00",
          "url": "https://dart.fss.or.kr/dsaf001/main.do?rcpNo=20260422900377",
          "glossaryTermId": "big_contract"
        },
        {
          "id": "20260422000460",
          "source": "dart",
          "company": "이뮨온시아",
          "companyCode": "424870",
          "headline": "임원ㆍ주요주주특정증권등소유상황보고서",
          "summary": "",
          "score": 70,
          "direction": "mixed",
          "scope": "domestic",
          "time": "2026-04-22T00:00:00",
          "url": "https://dart.fss.or.kr/dsaf001/main.do?rcpNo=20260422000460",
          "glossaryTermId": "insider_trade"
        }
      ],
      "foreign": []
    }
  },
  "glossary": {
    "convertible_bond": {
      "shortLabel": "전환사채 발행",
      "explanation": "일정 조건에서 주식으로 전환할 수 있는 채권을 발행하는 결정이에요. 자금 조달은 긍정이지만 전환 시 지분 희석이 따라와요. 전환가·전환조건이 핵심 변수예요.",
      "direction": "mixed"
    },
    "tentative_earnings": {
      "shortLabel": "잠정 실적",
      "explanation": "분기 종료 후 약 1개월 안에 잠정 영업이익·매출을 발표해요. 애널리스트 컨센서스 대비 서프라이즈/쇼크 여부가 핵심이에요. 확정 실적은 분기보고서에서 다시 확인돼요.",
      "direction": "mixed"
    },
    "insider_trade": {
      "shortLabel": "내부자 매매",
      "explanation": "회사 임원이나 5% 이상 주요주주가 자사 주식을 사고팔면 5영업일 내에 공시해요. 내부 정보에 밝은 사람의 거래라서 시장이 주목해요. 매수는 '저평가로 본다', 매도는 '차익 실현 또는 부정 전망'으로 통상 해석해요.",
      "direction": "mixed"
    },
    "big_contract": {
      "shortLabel": "대형 수주",
      "explanation": "매출 10% 이상 규모의 단일 공급계약이 체결되면 공시 의무가 있어요. 신규 매출 가시성을 주는 긍정 신호로 해석해요. 계약 금액·상대방·기간이 핵심이에요. 체결 후 취소도 종종 있어요.",
      "direction": "positive"
    },
    "self_stock_sell": {
      "shortLabel": "자사주 처분",
      "explanation": "회사가 보유 중이던 자사주를 팔거나 직원 보상(ESOP)에 쓰는 결정이에요. 매각이면 수급상 부담, ESOP면 중립~긍정으로 해석이 갈려요. 처분 방식과 사유가 핵심이에요.",
      "direction": "mixed"
    }
  }
}